odoo/addons/account_payment_netting/README.rst
odoo/addons/account_payment_netting/__init__.py
odoo/addons/account_payment_netting/__manifest__.py
odoo/addons/account_payment_netting/i18n/account_payment_netting.pot
odoo/addons/account_payment_netting/models/__init__.py
odoo/addons/account_payment_netting/models/account_invoice.py
odoo/addons/account_payment_netting/models/account_payment.py
odoo/addons/account_payment_netting/readme/CONTRIBUTORS.rst
odoo/addons/account_payment_netting/readme/DESCRIPTION.rst
odoo/addons/account_payment_netting/readme/USAGE.rst
odoo/addons/account_payment_netting/static/description/icon.png
odoo/addons/account_payment_netting/static/description/index.html
odoo/addons/account_payment_netting/tests/__init__.py
odoo/addons/account_payment_netting/tests/test_account_payment_netting.py
odoo/addons/account_payment_netting/views/account_invoice_view.xml
odoo/addons/account_payment_netting/views/account_payment_view.xml
odoo12_addon_account_payment_netting-12.0.1.0.1.dist-info/METADATA
odoo12_addon_account_payment_netting-12.0.1.0.1.dist-info/WHEEL
odoo12_addon_account_payment_netting-12.0.1.0.1.dist-info/top_level.txt
odoo12_addon_account_payment_netting-12.0.1.0.1.dist-info/RECORD
